{
    "openapi": "3.0.0",
    "info": {
        "title": "Pet Shop API - Swagger Documentation",
        "description": "Solution to the Pet Shop Challenge",
        "contact": "SiddhantBaviskar@outlook.com",
        "version": "1.0.0"
    },
    "paths": {
        "/api/v1/admin/create": {
            "post": {
                "tags": [
                    "Admin"
                ],
                "summary": "Create an Admin account",
                "description": "Test Description",
                "operationId": "admin-create",
                "requestBody": {
                    "required": true,
                    "content": {
                        "application/x-www-form-urlencoded": {
                            "schema": {
                                "required": [
                                    "first_name",
                                    "last_name",
                                    "email",
                                    "password",
                                    "password_confirmation",
                                    "avatar",
                                    "address",
                                    "phone_number"
                                ],
                                "properties": {
                                    "first_name": {
                                        "description": "User firstname",
                                        "type": "string"
                                    },
                                    "last_name": {
                                        "description": "User lastname",
                                        "type": "string"
                                    },
                                    "email": {
                                        "description": "User email",
                                        "type": "string"
                                    },
                                    "password": {
                                        "description": "User password",
                                        "type": "string"
                                    },
                                    "password_confirmation": {
                                        "description": "User password",
                                        "type": "string"
                                    },
                                    "avatar": {
                                        "description": "Avatar image UUID",
                                        "type": "string"
                                    },
                                    "address": {
                                        "description": "User main address",
                                        "type": "string"
                                    },
                                    "phone_number": {
                                        "description": "User main phone number",
                                        "type": "string"
                                    },
                                    "is_marketing": {
                                        "description": "User marketing preferences",
                                        "type": "string",
                                        "enum": [
                                            "0",
                                            "1"
                                        ]
                                    }
                                },
                                "type": "object"
                            }
                        }
                    }
                },
                "responses": {
                    "200": {
                        "description": "OK"
                    },
                    "401": {
                        "description": "Unauthorized"
                    },
                    "404": {
                        "description": "Page not found"
                    },
                    "422": {
                        "description": "Unprocessable Entity"
                    },
                    "500": {
                        "description": "Internal server error"
                    }
                }
            }
        },
        "/api/v1/admin/login": {
            "post": {
                "tags": [
                    "Admin"
                ],
                "summary": "Login an Admin account",
                "description": "Test Description",
                "operationId": "admin-login",
                "requestBody": {
                    "required": true,
                    "content": {
                        "application/x-www-form-urlencoded": {
                            "schema": {
                                "required": [
                                    "email",
                                    "password"
                                ],
                                "properties": {
                                    "email": {
                                        "description": "Admin email",
                                        "type": "string"
                                    },
                                    "password": {
                                        "description": "Admin password",
                                        "type": "string"
                                    }
                                },
                                "type": "object"
                            }
                        }
                    }
                },
                "responses": {
                    "200": {
                        "description": "OK"
                    },
                    "401": {
                        "description": "Unauthorized"
                    },
                    "404": {
                        "description": "Page not found"
                    },
                    "422": {
                        "description": "Unprocessable Entity"
                    },
                    "500": {
                        "description": "Internal server error"
                    }
                }
            }
        },
        "/api/v1/admin/logout": {
            "get": {
                "tags": [
                    "Admin"
                ],
                "summary": "Logout an Admin account",
                "description": "Test Description",
                "operationId": "admin-logout",
                "responses": {
                    "200": {
                        "description": "OK"
                    },
                    "401": {
                        "description": "Unauthorized"
                    },
                    "404": {
                        "description": "Page not found"
                    },
                    "422": {
                        "description": "Unprocessable Entity"
                    },
                    "500": {
                        "description": "Internal server error"
                    }
                }
            }
        },
        "/api/v1/admin/user-delete/{uuid}": {
            "delete": {
                "tags": [
                    "Admin"
                ],
                "summary": "Edit a User account",
                "description": "Test Description",
                "operationId": "admin-user-delete",
                "parameters": [
                    {
                        "name": "uuid",
                        "in": "path",
                        "required": true,
                        "schema": {
                            "type": "string"
                        }
                    }
                ],
                "responses": {
                    "200": {
                        "description": "OK"
                    },
                    "401": {
                        "description": "Unauthorized"
                    },
                    "404": {
                        "description": "Page not found"
                    },
                    "422": {
                        "description": "Unprocessable Entity"
                    },
                    "500": {
                        "description": "Internal server error"
                    }
                },
                "security": [
                    {
                        "bearerAuth": []
                    }
                ]
            }
        },
        "/api/v1/admin/user-edit/{uuid}": {
            "put": {
                "tags": [
                    "Admin"
                ],
                "summary": "Edit a User account",
                "description": "Test Description",
                "operationId": "admin-user-edit",
                "parameters": [
                    {
                        "name": "uuid",
                        "in": "path",
                        "required": true,
                        "schema": {
                            "type": "string"
                        }
                    }
                ],
                "requestBody": {
                    "required": true,
                    "content": {
                        "application/x-www-form-urlencoded": {
                            "schema": {
                                "required": [
                                    "first_name",
                                    "last_name",
                                    "email",
                                    "password",
                                    "password_confirmation",
                                    "address",
                                    "phone_number"
                                ],
                                "properties": {
                                    "first_name": {
                                        "description": "User firstname",
                                        "type": "string"
                                    },
                                    "last_name": {
                                        "description": "User lastname",
                                        "type": "string"
                                    },
                                    "email": {
                                        "description": "User email",
                                        "type": "string"
                                    },
                                    "password": {
                                        "description": "User password",
                                        "type": "string"
                                    },
                                    "password_confirmation": {
                                        "description": "User password",
                                        "type": "string"
                                    },
                                    "avatar": {
                                        "description": "Avatar image UUID",
                                        "type": "string"
                                    },
                                    "address": {
                                        "description": "User main address",
                                        "type": "string"
                                    },
                                    "phone_number": {
                                        "description": "User main phone number",
                                        "type": "string"
                                    },
                                    "is_marketing": {
                                        "description": "User marketing preferences",
                                        "type": "string",
                                        "enum": [
                                            "0",
                                            "1"
                                        ]
                                    }
                                },
                                "type": "object"
                            }
                        }
                    }
                },
                "responses": {
                    "200": {
                        "description": "OK"
                    },
                    "401": {
                        "description": "Unauthorized"
                    },
                    "404": {
                        "description": "Page not found"
                    },
                    "422": {
                        "description": "Unprocessable Entity"
                    },
                    "500": {
                        "description": "Internal server error"
                    }
                },
                "security": [
                    {
                        "bearerAuth": []
                    }
                ]
            }
        },
        "/api/v1/admin/user-listing": {
            "get": {
                "tags": [
                    "Admin"
                ],
                "summary": "List all users",
                "description": "Test Description",
                "operationId": "admin-user-listing",
                "parameters": [
                    {
                        "name": "page",
                        "in": "query",
                        "required": false,
                        "schema": {
                            "type": "integer"
                        }
                    },
                    {
                        "name": "limit",
                        "in": "query",
                        "required": false,
                        "schema": {
                            "type": "integer"
                        }
                    },
                    {
                        "name": "sortBy",
                        "in": "query",
                        "required": false,
                        "schema": {
                            "type": "string"
                        }
                    },
                    {
                        "name": "desc",
                        "in": "query",
                        "required": false,
                        "schema": {
                            "type": "boolean"
                        }
                    },
                    {
                        "name": "first_name",
                        "in": "query",
                        "required": false,
                        "schema": {
                            "type": "string"
                        }
                    },
                    {
                        "name": "email",
                        "in": "query",
                        "required": false,
                        "schema": {
                            "type": "string"
                        }
                    },
                    {
                        "name": "phone",
                        "in": "query",
                        "required": false,
                        "schema": {
                            "type": "string"
                        }
                    },
                    {
                        "name": "address",
                        "in": "query",
                        "required": false,
                        "schema": {
                            "type": "string"
                        }
                    },
                    {
                        "name": "created_at",
                        "in": "query",
                        "required": false,
                        "schema": {
                            "type": "string"
                        }
                    },
                    {
                        "name": "marketing",
                        "in": "query",
                        "required": false,
                        "schema": {
                            "type": "string",
                            "enum": [
                                "0",
                                "1"
                            ]
                        }
                    }
                ],
                "responses": {
                    "200": {
                        "description": "OK"
                    },
                    "401": {
                        "description": "Unauthorized"
                    },
                    "404": {
                        "description": "Page not found"
                    },
                    "422": {
                        "description": "Unprocessable Entity"
                    },
                    "500": {
                        "description": "Internal server error"
                    }
                },
                "security": [
                    {
                        "bearerAuth": []
                    }
                ]
            }
        },
        "/api/v1/categories": {
            "get": {
                "tags": [
                    "Categories"
                ],
                "summary": "List all categories",
                "description": "Test Description",
                "operationId": "categories-listing",
                "parameters": [
                    {
                        "name": "page",
                        "in": "query",
                        "required": false,
                        "schema": {
                            "type": "integer"
                        }
                    },
                    {
                        "name": "limit",
                        "in": "query",
                        "required": false,
                        "schema": {
                            "type": "integer"
                        }
                    },
                    {
                        "name": "sortBy",
                        "in": "query",
                        "required": false,
                        "schema": {
                            "type": "string"
                        }
                    },
                    {
                        "name": "desc",
                        "in": "query",
                        "required": false,
                        "schema": {
                            "type": "boolean"
                        }
                    }
                ],
                "responses": {
                    "200": {
                        "description": "OK"
                    },
                    "401": {
                        "description": "Unauthorized"
                    },
                    "404": {
                        "description": "Page not found"
                    },
                    "422": {
                        "description": "Unprocessable Entity"
                    },
                    "500": {
                        "description": "Internal server error"
                    }
                }
            }
        },
        "/api/v1/category/create": {
            "post": {
                "tags": [
                    "Categories"
                ],
                "summary": "Create a new category",
                "description": "Test Description",
                "operationId": "categories-create",
                "requestBody": {
                    "required": true,
                    "content": {
                        "application/x-www-form-urlencoded": {
                            "schema": {
                                "required": [
                                    "title"
                                ],
                                "properties": {
                                    "title": {
                                        "type": "string"
                                    }
                                },
                                "type": "object"
                            }
                        }
                    }
                },
                "responses": {
                    "200": {
                        "description": "OK"
                    },
                    "401": {
                        "description": "Unauthorized"
                    },
                    "404": {
                        "description": "Page not found"
                    },
                    "422": {
                        "description": "Unprocessable Entity"
                    },
                    "500": {
                        "description": "Internal server error"
                    }
                },
                "security": [
                    {
                        "bearerAuth": []
                    }
                ]
            }
        },
        "/api/v1/category/{uuid}": {
            "get": {
                "tags": [
                    "Categories"
                ],
                "summary": "Fetch a category",
                "description": "Test Description",
                "operationId": "categories-read",
                "parameters": [
                    {
                        "name": "uuid",
                        "in": "path",
                        "required": true,
                        "schema": {
                            "type": "string"
                        }
                    }
                ],
                "responses": {
                    "200": {
                        "description": "OK"
                    },
                    "401": {
                        "description": "Unauthorized"
                    },
                    "404": {
                        "description": "Page not found"
                    },
                    "422": {
                        "description": "Unprocessable Entity"
                    },
                    "500": {
                        "description": "Internal server error"
                    }
                }
            },
            "put": {
                "tags": [
                    "Categories"
                ],
                "summary": "Update an existing category",
                "description": "Test Description",
                "operationId": "categories-update",
                "parameters": [
                    {
                        "name": "uuid",
                        "in": "path",
                        "required": true,
                        "schema": {
                            "type": "string"
                        }
                    }
                ],
                "requestBody": {
                    "required": true,
                    "content": {
                        "application/x-www-form-urlencoded": {
                            "schema": {
                                "required": [
                                    "title"
                                ],
                                "properties": {
                                    "title": {
                                        "type": "string"
                                    }
                                },
                                "type": "object"
                            }
                        }
                    }
                },
                "responses": {
                    "200": {
                        "description": "OK"
                    },
                    "401": {
                        "description": "Unauthorized"
                    },
                    "404": {
                        "description": "Page not found"
                    },
                    "422": {
                        "description": "Unprocessable Entity"
                    },
                    "500": {
                        "description": "Internal server error"
                    }
                },
                "security": [
                    {
                        "bearerAuth": []
                    }
                ]
            },
            "delete": {
                "tags": [
                    "Categories"
                ],
                "summary": "delete an existing category",
                "description": "Test Description",
                "operationId": "categories-delete",
                "parameters": [
                    {
                        "name": "uuid",
                        "in": "path",
                        "required": true,
                        "schema": {
                            "type": "string"
                        }
                    }
                ],
                "responses": {
                    "200": {
                        "description": "OK"
                    },
                    "401": {
                        "description": "Unauthorized"
                    },
                    "404": {
                        "description": "Page not found"
                    },
                    "422": {
                        "description": "Unprocessable Entity"
                    },
                    "500": {
                        "description": "Internal server error"
                    }
                },
                "security": [
                    {
                        "bearerAuth": []
                    }
                ]
            }
        },
        "/api/v1/file/upload": {
            "post": {
                "tags": [
                    "File"
                ],
                "summary": "Upload a file",
                "description": "Test Description",
                "operationId": "file-upload",
                "requestBody": {
                    "required": true,
                    "content": {
                        "multipart/form-data": {
                            "schema": {
                                "required": [
                                    "file"
                                ],
                                "properties": {
                                    "file": {
                                        "description": "file to upload",
                                        "type": "string",
                                        "format": "binary"
                                    }
                                },
                                "type": "object"
                            }
                        }
                    }
                },
                "responses": {
                    "200": {
                        "description": "OK"
                    },
                    "401": {
                        "description": "Unauthorized"
                    },
                    "404": {
                        "description": "Page not found"
                    },
                    "422": {
                        "description": "Unprocessable Entity"
                    },
                    "500": {
                        "description": "Internal server error"
                    }
                },
                "security": [
                    {
                        "bearerAuth": []
                    }
                ]
            }
        },
        "/api/v1/file/{uuid}": {
            "get": {
                "tags": [
                    "File"
                ],
                "summary": "Read a file",
                "description": "Test Description",
                "operationId": "file-read",
                "parameters": [
                    {
                        "name": "uuid",
                        "in": "path",
                        "required": true,
                        "schema": {
                            "type": "string"
                        }
                    }
                ],
                "responses": {
                    "200": {
                        "description": "OK"
                    },
                    "401": {
                        "description": "Unauthorized"
                    },
                    "404": {
                        "description": "Page not found"
                    },
                    "422": {
                        "description": "Unprocessable Entity"
                    },
                    "500": {
                        "description": "Internal server error"
                    }
                }
            }
        },
        "/api/v1/user/forgot-password": {
            "post": {
                "tags": [
                    "User"
                ],
                "summary": "Creates a token to reset a user password",
                "description": "Test Description",
                "operationId": "user-forgot-pass",
                "parameters": [
                    {
                        "name": "email",
                        "in": "query",
                        "description": "User email",
                        "required": true,
                        "schema": {
                            "type": "string"
                        }
                    }
                ],
                "responses": {
                    "200": {
                        "description": "OK"
                    },
                    "401": {
                        "description": "Unauthorized"
                    },
                    "404": {
                        "description": "Page not found"
                    },
                    "422": {
                        "description": "Unprocessable Entity"
                    },
                    "500": {
                        "description": "Internal server error"
                    }
                }
            }
        },
        "/api/v1/payments": {
            "get": {
                "tags": [
                    "Payments"
                ],
                "summary": "List all payments",
                "description": "Test Description",
                "operationId": "payments-listing",
                "parameters": [
                    {
                        "name": "page",
                        "in": "query",
                        "required": false,
                        "schema": {
                            "type": "integer"
                        }
                    },
                    {
                        "name": "limit",
                        "in": "query",
                        "required": false,
                        "schema": {
                            "type": "integer"
                        }
                    },
                    {
                        "name": "sortBy",
                        "in": "query",
                        "required": false,
                        "schema": {
                            "type": "string"
                        }
                    },
                    {
                        "name": "desc",
                        "in": "query",
                        "required": false,
                        "schema": {
                            "type": "boolean"
                        }
                    }
                ],
                "responses": {
                    "200": {
                        "description": "OK"
                    },
                    "401": {
                        "description": "Unauthorized"
                    },
                    "404": {
                        "description": "Page not found"
                    },
                    "422": {
                        "description": "Unprocessable Entity"
                    },
                    "500": {
                        "description": "Internal server error"
                    }
                },
                "security": [
                    {
                        "bearerAuth": []
                    }
                ]
            }
        },
        "/api/v1/payment/create": {
            "post": {
                "tags": [
                    "Payments"
                ],
                "summary": "Create a new payment",
                "description": "Test Description",
                "operationId": "payments-create",
                "requestBody": {
                    "required": true,
                    "content": {
                        "application/x-www-form-urlencoded": {
                            "schema": {
                                "required": [
                                    "type",
                                    "details"
                                ],
                                "properties": {
                                    "type": {
                                        "description": "Payment type",
                                        "type": "string",
                                        "enum": [
                                            "credit_card",
                                            "cash_on_delivery",
                                            "bank_transfer"
                                        ]
                                    },
                                    "details": {
                                        "description": "Review documentation for the payment type JSON format",
                                        "type": "object"
                                    }
                                },
                                "type": "object"
                            }
                        }
                    }
                },
                "responses": {
                    "200": {
                        "description": "OK"
                    },
                    "401": {
                        "description": "Unauthorized"
                    },
                    "404": {
                        "description": "Page not found"
                    },
                    "422": {
                        "description": "Unprocessable Entity"
                    },
                    "500": {
                        "description": "Internal server error"
                    }
                },
                "security": [
                    {
                        "bearerAuth": []
                    }
                ]
            }
        },
        "/api/v1/payment/{uuid}": {
            "get": {
                "tags": [
                    "Payments"
                ],
                "summary": "Fetch a payment",
                "description": "Test Description",
                "operationId": "payments-read",
                "parameters": [
                    {
                        "name": "uuid",
                        "in": "path",
                        "required": true,
                        "schema": {
                            "type": "string"
                        }
                    }
                ],
                "responses": {
                    "200": {
                        "description": "OK"
                    },
                    "401": {
                        "description": "Unauthorized"
                    },
                    "404": {
                        "description": "Page not found"
                    },
                    "422": {
                        "description": "Unprocessable Entity"
                    },
                    "500": {
                        "description": "Internal server error"
                    }
                },
                "security": [
                    {
                        "bearerAuth": []
                    }
                ]
            },
            "put": {
                "tags": [
                    "Payments"
                ],
                "summary": "Update an existing payment",
                "description": "Test Description",
                "operationId": "payments-update",
                "parameters": [
                    {
                        "name": "uuid",
                        "in": "path",
                        "required": true,
                        "schema": {
                            "type": "string"
                        }
                    }
                ],
                "requestBody": {
                    "required": true,
                    "content": {
                        "application/x-www-form-urlencoded": {
                            "schema": {
                                "required": [
                                    "type",
                                    "details"
                                ],
                                "properties": {
                                    "type": {
                                        "description": "Payment type",
                                        "type": "string",
                                        "enum": [
                                            "credit_card",
                                            "cash_on_delivery",
                                            "bank_transfer"
                                        ]
                                    },
                                    "details": {
                                        "description": "Review documentation for the payment type JSON format",
                                        "type": "object"
                                    }
                                },
                                "type": "object"
                            }
                        }
                    }
                },
                "responses": {
                    "200": {
                        "description": "OK"
                    },
                    "401": {
                        "description": "Unauthorized"
                    },
                    "404": {
                        "description": "Page not found"
                    },
                    "422": {
                        "description": "Unprocessable Entity"
                    },
                    "500": {
                        "description": "Internal server error"
                    }
                },
                "security": [
                    {
                        "bearerAuth": []
                    }
                ]
            },
            "delete": {
                "tags": [
                    "Payments"
                ],
                "summary": "delete an existing payment",
                "description": "Test Description",
                "operationId": "payments-delete",
                "parameters": [
                    {
                        "name": "uuid",
                        "in": "path",
                        "required": true,
                        "schema": {
                            "type": "string"
                        }
                    }
                ],
                "responses": {
                    "200": {
                        "description": "OK"
                    },
                    "401": {
                        "description": "Unauthorized"
                    },
                    "404": {
                        "description": "Page not found"
                    },
                    "422": {
                        "description": "Unprocessable Entity"
                    },
                    "500": {
                        "description": "Internal server error"
                    }
                },
                "security": [
                    {
                        "bearerAuth": []
                    }
                ]
            }
        },
        "/api/v1/products": {
            "get": {
                "tags": [
                    "Products"
                ],
                "summary": "List all products",
                "description": "Test Description",
                "operationId": "products-listing",
                "parameters": [
                    {
                        "name": "page",
                        "in": "query",
                        "required": false,
                        "schema": {
                            "type": "integer"
                        }
                    },
                    {
                        "name": "limit",
                        "in": "query",
                        "required": false,
                        "schema": {
                            "type": "integer"
                        }
                    },
                    {
                        "name": "sortBy",
                        "in": "query",
                        "required": false,
                        "schema": {
                            "type": "string"
                        }
                    },
                    {
                        "name": "desc",
                        "in": "query",
                        "required": false,
                        "schema": {
                            "type": "boolean"
                        }
                    }
                ],
                "responses": {
                    "200": {
                        "description": "OK"
                    },
                    "401": {
                        "description": "Unauthorized"
                    },
                    "404": {
                        "description": "Page not found"
                    },
                    "422": {
                        "description": "Unprocessable Entity"
                    },
                    "500": {
                        "description": "Internal server error"
                    }
                }
            }
        },
        "/api/v1/product/create": {
            "post": {
                "tags": [
                    "Products"
                ],
                "summary": "Create a new product",
                "description": "Test Description",
                "operationId": "products-create",
                "requestBody": {
                    "required": true,
                    "content": {
                        "application/x-www-form-urlencoded": {
                            "schema": {
                                "required": [
                                    "category_uuid",
                                    "title",
                                    "price",
                                    "description",
                                    "metadata"
                                ],
                                "properties": {
                                    "category_uuid": {
                                        "description": "Category UUID",
                                        "type": "string"
                                    },
                                    "title": {
                                        "description": "Product title",
                                        "type": "string"
                                    },
                                    "price": {
                                        "description": "Product price",
                                        "type": "number"
                                    },
                                    "description": {
                                        "description": "Product description",
                                        "type": "string"
                                    },
                                    "metadata": {
                                        "description": "Product metadata",
                                        "properties": {
                                            "image": {
                                                "type": "string"
                                            },
                                            "brand": {
                                                "type": "string"
                                            }
                                        },
                                        "type": "object"
                                    }
                                },
                                "type": "object"
                            }
                        }
                    }
                },
                "responses": {
                    "200": {
                        "description": "OK"
                    },
                    "401": {
                        "description": "Unauthorized"
                    },
                    "404": {
                        "description": "Page not found"
                    },
                    "422": {
                        "description": "Unprocessable Entity"
                    },
                    "500": {
                        "description": "Internal server error"
                    }
                },
                "security": [
                    {
                        "bearerAuth": []
                    }
                ]
            }
        },
        "/api/v1/product/{uuid}": {
            "get": {
                "tags": [
                    "Products"
                ],
                "summary": "Fetch a product",
                "description": "Test Description",
                "operationId": "products-read",
                "parameters": [
                    {
                        "name": "uuid",
                        "in": "path",
                        "required": true,
                        "schema": {
                            "type": "string"
                        }
                    }
                ],
                "responses": {
                    "200": {
                        "description": "OK"
                    },
                    "401": {
                        "description": "Unauthorized"
                    },
                    "404": {
                        "description": "Page not found"
                    },
                    "422": {
                        "description": "Unprocessable Entity"
                    },
                    "500": {
                        "description": "Internal server error"
                    }
                }
            },
            "put": {
                "tags": [
                    "Products"
                ],
                "summary": "Update an existing product",
                "description": "Test Description",
                "operationId": "products-update",
                "parameters": [
                    {
                        "name": "uuid",
                        "in": "path",
                        "description": "UUID parameter",
                        "required": true,
                        "schema": {
                            "type": "string"
                        }
                    }
                ],
                "requestBody": {
                    "required": true,
                    "content": {
                        "application/x-www-form-urlencoded": {
                            "schema": {
                                "required": [
                                    "category_uuid",
                                    "title",
                                    "price",
                                    "description",
                                    "metadata"
                                ],
                                "properties": {
                                    "category_uuid": {
                                        "description": "Category UUID parameter",
                                        "type": "string"
                                    },
                                    "title": {
                                        "description": "Product title",
                                        "type": "string"
                                    },
                                    "price": {
                                        "description": "Product price",
                                        "type": "number"
                                    },
                                    "description": {
                                        "description": "Product description",
                                        "type": "string"
                                    },
                                    "metadata": {
                                        "description": "Product metadata",
                                        "properties": {
                                            "image": {
                                                "type": "string"
                                            },
                                            "brand": {
                                                "type": "string"
                                            }
                                        },
                                        "type": "object"
                                    }
                                },
                                "type": "object"
                            }
                        }
                    }
                },
                "responses": {
                    "200": {
                        "description": "OK"
                    },
                    "401": {
                        "description": "Unauthorized"
                    },
                    "404": {
                        "description": "Page not found"
                    },
                    "422": {
                        "description": "Unprocessable Entity"
                    },
                    "500": {
                        "description": "Internal server error"
                    }
                },
                "security": [
                    {
                        "bearerAuth": []
                    }
                ]
            },
            "delete": {
                "tags": [
                    "Products"
                ],
                "summary": "delete an existing product",
                "description": "Test Description",
                "operationId": "products-delete",
                "parameters": [
                    {
                        "name": "uuid",
                        "in": "path",
                        "required": true,
                        "schema": {
                            "type": "string"
                        }
                    }
                ],
                "responses": {
                    "200": {
                        "description": "OK"
                    },
                    "401": {
                        "description": "Unauthorized"
                    },
                    "404": {
                        "description": "Page not found"
                    },
                    "422": {
                        "description": "Unprocessable Entity"
                    },
                    "500": {
                        "description": "Internal server error"
                    }
                },
                "security": [
                    {
                        "bearerAuth": []
                    }
                ]
            }
        },
        "/api/v1/user/reset-password-token": {
            "post": {
                "tags": [
                    "User"
                ],
                "summary": "Reset a user password with the a token",
                "description": "Test Description",
                "operationId": "user-reset-pass-token",
                "parameters": [
                    {
                        "name": "token",
                        "in": "query",
                        "description": "User reset token",
                        "required": true,
                        "schema": {
                            "type": "string"
                        }
                    },
                    {
                        "name": "email",
                        "in": "query",
                        "description": "User email",
                        "required": true,
                        "schema": {
                            "type": "string"
                        }
                    },
                    {
                        "name": "password",
                        "in": "query",
                        "description": "User password",
                        "required": true,
                        "schema": {
                            "type": "string"
                        }
                    },
                    {
                        "name": "password_confirmation",
                        "in": "query",
                        "description": "User password",
                        "required": true,
                        "schema": {
                            "type": "string"
                        }
                    }
                ],
                "responses": {
                    "200": {
                        "description": "OK"
                    },
                    "401": {
                        "description": "Unauthorized"
                    },
                    "404": {
                        "description": "Page not found"
                    },
                    "422": {
                        "description": "Unprocessable Entity"
                    },
                    "500": {
                        "description": "Internal server error"
                    }
                }
            }
        },
        "/api/v1/user/login": {
            "post": {
                "tags": [
                    "User"
                ],
                "summary": "Login an User account",
                "description": "Test Description",
                "operationId": "user-login",
                "requestBody": {
                    "required": true,
                    "content": {
                        "application/x-www-form-urlencoded": {
                            "schema": {
                                "required": [
                                    "email",
                                    "password"
                                ],
                                "properties": {
                                    "email": {
                                        "description": "User email",
                                        "type": "string"
                                    },
                                    "password": {
                                        "description": "User password",
                                        "type": "string"
                                    }
                                },
                                "type": "object"
                            }
                        }
                    }
                },
                "responses": {
                    "200": {
                        "description": "OK"
                    },
                    "401": {
                        "description": "Unauthorized"
                    },
                    "404": {
                        "description": "Page not found"
                    },
                    "422": {
                        "description": "Unprocessable Entity"
                    },
                    "500": {
                        "description": "Internal server error"
                    }
                }
            }
        },
        "/api/v1/user/logout": {
            "get": {
                "tags": [
                    "User"
                ],
                "summary": "Logout an User account",
                "description": "Test Description",
                "operationId": "user-logout",
                "responses": {
                    "200": {
                        "description": "OK"
                    },
                    "401": {
                        "description": "Unauthorized"
                    },
                    "404": {
                        "description": "Page not found"
                    },
                    "422": {
                        "description": "Unprocessable Entity"
                    },
                    "500": {
                        "description": "Internal server error"
                    }
                }
            }
        },
        "/api/v1/user": {
            "get": {
                "tags": [
                    "User"
                ],
                "summary": "View a User account",
                "description": "Test Description",
                "operationId": "user-read",
                "responses": {
                    "200": {
                        "description": "OK"
                    },
                    "401": {
                        "description": "Unauthorized"
                    },
                    "404": {
                        "description": "Page not found"
                    },
                    "422": {
                        "description": "Unprocessable Entity"
                    },
                    "500": {
                        "description": "Internal server error"
                    }
                },
                "security": [
                    {
                        "bearerAuth": []
                    }
                ]
            }
        },
        "/api/v1/user/create": {
            "post": {
                "tags": [
                    "User"
                ],
                "summary": "Create a User account",
                "description": "Test Description",
                "operationId": "user-create",
                "requestBody": {
                    "required": true,
                    "content": {
                        "application/x-www-form-urlencoded": {
                            "schema": {
                                "required": [
                                    "first_name",
                                    "last_name",
                                    "email",
                                    "password",
                                    "password_confirmation",
                                    "address",
                                    "phone_number"
                                ],
                                "properties": {
                                    "first_name": {
                                        "description": "User firstname",
                                        "type": "string"
                                    },
                                    "last_name": {
                                        "description": "User lastname",
                                        "type": "string"
                                    },
                                    "email": {
                                        "description": "User email",
                                        "type": "string"
                                    },
                                    "password": {
                                        "description": "User password",
                                        "type": "string"
                                    },
                                    "password_confirmation": {
                                        "description": "User password",
                                        "type": "string"
                                    },
                                    "avatar": {
                                        "description": "Avatar image UUID",
                                        "type": "string"
                                    },
                                    "address": {
                                        "description": "User main address",
                                        "type": "string"
                                    },
                                    "phone_number": {
                                        "description": "User main phone number",
                                        "type": "string"
                                    },
                                    "is_marketing": {
                                        "description": "User marketing preferences",
                                        "type": "string",
                                        "enum": [
                                            "0",
                                            "1"
                                        ]
                                    }
                                },
                                "type": "object"
                            }
                        }
                    }
                },
                "responses": {
                    "200": {
                        "description": "OK"
                    },
                    "401": {
                        "description": "Unauthorized"
                    },
                    "404": {
                        "description": "Page not found"
                    },
                    "422": {
                        "description": "Unprocessable Entity"
                    },
                    "500": {
                        "description": "Internal server error"
                    }
                }
            }
        },
        "/api/v1/user/edit": {
            "put": {
                "tags": [
                    "User"
                ],
                "summary": "Update a User account",
                "description": "Test Description",
                "operationId": "user-update",
                "requestBody": {
                    "required": true,
                    "content": {
                        "application/x-www-form-urlencoded": {
                            "schema": {
                                "required": [
                                    "first_name",
                                    "last_name",
                                    "email",
                                    "password",
                                    "password_confirmation",
                                    "address",
                                    "phone_number"
                                ],
                                "properties": {
                                    "first_name": {
                                        "description": "User firstname",
                                        "type": "string"
                                    },
                                    "last_name": {
                                        "description": "User lastname",
                                        "type": "string"
                                    },
                                    "email": {
                                        "description": "User email",
                                        "type": "string"
                                    },
                                    "password": {
                                        "description": "User password",
                                        "type": "string"
                                    },
                                    "password_confirmation": {
                                        "description": "User password",
                                        "type": "string"
                                    },
                                    "avatar": {
                                        "description": "Avatar image UUID",
                                        "type": "string"
                                    },
                                    "address": {
                                        "description": "User main address",
                                        "type": "string"
                                    },
                                    "phone_number": {
                                        "description": "User main phone number",
                                        "type": "string"
                                    },
                                    "is_marketing": {
                                        "description": "User marketing preferences",
                                        "type": "string",
                                        "enum": [
                                            "0",
                                            "1"
                                        ]
                                    }
                                },
                                "type": "object"
                            }
                        }
                    }
                },
                "responses": {
                    "200": {
                        "description": "OK"
                    },
                    "401": {
                        "description": "Unauthorized"
                    },
                    "404": {
                        "description": "Page not found"
                    },
                    "422": {
                        "description": "Unprocessable Entity"
                    },
                    "500": {
                        "description": "Internal server error"
                    }
                },
                "security": [
                    {
                        "bearerAuth": []
                    }
                ]
            }
        }
    },
    "components": {
        "securitySchemes": {
            "bearerAuth": {
                "type": "http",
                "name": "bearerAuth",
                "in": "header",
                "bearerFormat": "JWT",
                "scheme": "bearer"
            }
        }
    }
}